commah/__init__.py
commah/__version__.py
commah/commah.py
commah/cosmology_list.py
commah/tests/__init__.py
commah/tests/test_commah.py
commah-0.3.dist-info/AUTHORS.rst
commah-0.3.dist-info/LICENSE
commah-0.3.dist-info/METADATA
commah-0.3.dist-info/WHEEL
commah-0.3.dist-info/top_level.txt
commah-0.3.dist-info/RECORD
