Metadata-Version: 2.1
Name: commah
Version: 0.3
Summary: Get conc - mass or accretion history for any cosmology
Home-page: https://github.com/astroduff/commah
Author: Alan Duffy
Author-email: mail@alanrduffy.com
License: BSD
Download-URL: https://github.com/astroduff/commah/tarball/0.3
Keywords: commah,cosmology,astronomy,NFW,concentration,accretion
Platform: UNKNOWN
Classifier: Development Status :: 2 - Pre-Alpha
Classifier: Intended Audience :: Developers
Classifier: License :: OSI Approved :: BSD License
Classifier: Natural Language :: English
Classifier: Programming Language :: Python
Classifier: Programming Language :: Python :: 2
Classifier: Programming Language :: Python :: 2.7
Classifier: Programming Language :: Python :: 3
Classifier: Programming Language :: Python :: 3.5
Classifier: Programming Language :: Python :: 3.6
Classifier: Programming Language :: Python :: 3.7
Requires-Python: >=2.7, !=3.0.*, !=3.1.*, !=3.2.*, !=3.3.*, !=3.4.*, <4
Requires-Dist: numpy (>=1.4)
Requires-Dist: scipy (>=0.13)
Requires-Dist: cosmolopy (>=0.4)
